sp_package/__init__.py
sp_package/sphere_module.py
sp_package-0.1.0.dist-info/METADATA
sp_package-0.1.0.dist-info/WHEEL
sp_package-0.1.0.dist-info/top_level.txt
sp_package-0.1.0.dist-info/RECORD
