Metadata-Version: 2.4
Name: sp_package
Version: 0.1.0
Summary: A simple example package with math, string, and data utilities.
Home-page: https://github.com/paytai/sp_package
Author: Yok
Author-email: raseljone.com@gmail.com
Requires-Python: >=3.7
Dynamic: author
Dynamic: author-email
Dynamic: description
Dynamic: description-content-type
Dynamic: home-page
Dynamic: requires-python
Dynamic: summary
